zmkx/__init__.py
zmkx/comm_pb2.py
zmkx/delimited.py
zmkx-0.3.0.data/scripts/zmkx
zmkx-0.3.0.dist-info/LICENSE
zmkx-0.3.0.dist-info/METADATA
zmkx-0.3.0.dist-info/WHEEL
zmkx-0.3.0.dist-info/top_level.txt
zmkx-0.3.0.dist-info/RECORD
