Metadata-Version: 2.1
Name: zmkx
Version: 0.3.0
Summary: Python client for ZMKX
Home-page: https://github.com/xingrz/zmkx-sdk
Author: XiNGRZ
Author-email: hi@xingrz.me
License: MIT
License-File: LICENSE
Requires-Dist: hid >=1.0.5
Requires-Dist: protobuf >=3.20.1
Requires-Dist: inquirer >=3.1.3
Requires-Dist: pillow >=9.5.0
